pip_venv_sure.py
pip_venv_sure-0.1.1.dist-info/LICENSE
pip_venv_sure-0.1.1.dist-info/METADATA
pip_venv_sure-0.1.1.dist-info/WHEEL
pip_venv_sure-0.1.1.dist-info/entry_points.txt
pip_venv_sure-0.1.1.dist-info/top_level.txt
pip_venv_sure-0.1.1.dist-info/RECORD
