Metadata-Version: 2.1
Name: pip-venv-sure
Version: 0.1.1
Summary: A quick and easy way to make sure that you always install packages to virtualenv.
Home-page: https://github.com/Adwaith-Rajesh/pip-venv-sure
Author: Adwaith-Rajesh
Author-email: adwaithrajesh3180@gmail.com
License: MIT
Platform: UNKNOWN
Classifier: License :: OSI Approved :: MIT License
Classifier: Programming Language :: Python :: 3
Classifier: Programming Language :: Python :: 3 :: Only
Classifier: Programming Language :: Python :: 3.6
Classifier: Programming Language :: Python :: 3.7
Classifier: Programming Language :: Python :: 3.8
Classifier: Programming Language :: Python :: 3.9
Classifier: Programming Language :: Python :: 3.10
Requires-Python: >=3.6.1
License-File: LICENSE
